backtest/__init__.py
candlestream-1.0.2.dist-info/METADATA
candlestream-1.0.2.dist-info/WHEEL
candlestream-1.0.2.dist-info/top_level.txt
candlestream-1.0.2.dist-info/RECORD
